{
  "gretelarmfeg": {
    "balance": 10.635,
    "total_sent": 0,
    "last_updated": "2026-02-26"
  },
  "suteru": {
    "balance": 9.682,
    "total_sent": 0,
    "last_updated": "2026-02-26"
  },
  "diosarich": {
    "balance": 9.179,
    "total_sent": 0,
    "last_updated": "2026-02-26"
  },
  "vinzie1": {
    "balance": 7.762,
    "total_sent": 0,
    "last_updated": "2026-02-26"
  },
  "katiekate86": {
    "balance": 4.848,
    "total_sent": 0,
    "last_updated": "2026-02-26"
  },
  "jeanieviv84": {
    "balance": 3.9,
    "total_sent": 0,
    "last_updated": "2026-02-26"
  },
  "dreamrona": {
    "balance": 2.908,
    "total_sent": 0,
    "last_updated": "2026-02-26"
  },
  "vvodjiu": {
    "balance": 2.421,
    "total_sent": 0,
    "last_updated": "2026-02-26"
  },
  "blueoctopus": {
    "balance": 1.931,
    "total_sent": 0,
    "last_updated": "2026-02-26"
  },
  "hopefulsoul": {
    "balance": 1.854,
    "total_sent": 0,
    "last_updated": "2026-02-26"
  },
  "jocabanero4": {
    "balance": 1.487,
    "total_sent": 0,
    "last_updated": "2026-02-26"
  },
  "ronimarie82": {
    "balance": 1.46,
    "total_sent": 0,
    "last_updated": "2026-02-26"
  },
  "lj1728": {
    "balance": 1.45,
    "total_sent": 0,
    "last_updated": "2026-02-26"
  },
  "antonette": {
    "balance": 0.977,
    "total_sent": 0,
    "last_updated": "2026-02-26"
  },
  "krissymayol": {
    "balance": 0.975,
    "total_sent": 0,
    "last_updated": "2026-02-26"
  },
  "wanderelle": {
    "balance": 0.975,
    "total_sent": 0,
    "last_updated": "2026-02-26"
  },
  "crstypatata": {
    "balance": 0.966,
    "total_sent": 0,
    "last_updated": "2026-02-26"
  },
  "mayt": {
    "balance": 0.966,
    "total_sent": 0,
    "last_updated": "2026-02-26"
  },
  "lolitaanana001": {
    "balance": 0.962,
    "total_sent": 0,
    "last_updated": "2026-02-26"
  },
  "izyllah-aeon": {
    "balance": 0.903,
    "total_sent": 0,
    "last_updated": "2026-02-26"
  },
  "saijan19": {
    "balance": 0.486,
    "total_sent": 0,
    "last_updated": "2026-02-26"
  },
  "celestyne15": {
    "balance": 0.484,
    "total_sent": 0,
    "last_updated": "2026-02-26"
  },
  "heymariel": {
    "balance": 0.483,
    "total_sent": 0,
    "last_updated": "2026-02-26"
  },
  "rabino7515": {
    "balance": 0.483,
    "total_sent": 0,
    "last_updated": "2026-02-26"
  },
  "desyah07": {
    "balance": 0.393,
    "total_sent": 0,
    "last_updated": "2026-02-26"
  },
  "gracefulwrites": {
    "balance": 0.292,
    "total_sent": 0,
    "last_updated": "2026-02-26"
  },
  "rizz26": {
    "balance": 0.292,
    "total_sent": 0,
    "last_updated": "2026-02-26"
  },
  "daileen23": {
    "balance": 0.29,
    "total_sent": 0,
    "last_updated": "2026-02-26"
  },
  "arriane001": {
    "balance": 0.241,
    "total_sent": 0,
    "last_updated": "2026-02-26"
  },
  "sammify": {
    "balance": 0.174,
    "total_sent": 0,
    "last_updated": "2026-02-26"
  },
  "yhanyx87": {
    "balance": 0.135,
    "total_sent": 0,
    "last_updated": "2026-02-26"
  },
  "honeyjean24": {
    "balance": 0.098,
    "total_sent": 0,
    "last_updated": "2026-02-26"
  },
  "segundolhou29": {
    "balance": 0,
    "total_sent": 0,
    "last_updated": "2026-02-26"
  },
  "_meta": {
    "last_accumulated_date": "2026-02-25"
  },
  "joanna112890": {
    "balance": 0.051,
    "total_sent": 0,
    "last_updated": "2026-02-26"
  }
}