{
  "_meta": {
    "last_accumulated_date": "2026-07-14"
  },
  "gretelarmfeg": {
    "balance": 4.776,
    "total_sent": 91,
    "last_updated": "2026-07-15"
  },
  "suteru": {
    "balance": 4.044,
    "total_sent": 86,
    "last_updated": "2026-07-15"
  },
  "diosarich": {
    "balance": 4.37,
    "total_sent": 68,
    "last_updated": "2026-07-15"
  },
  "vinzie1": {
    "balance": 69.886,
    "total_sent": 0,
    "last_updated": "2026-07-15"
  },
  "katiekate86": {
    "balance": 4.548,
    "total_sent": 41,
    "last_updated": "2026-07-15"
  },
  "jeanieviv84": {
    "balance": 2.131,
    "total_sent": 33,
    "last_updated": "2026-07-15"
  },
  "dreamrona": {
    "balance": 3.224,
    "total_sent": 39,
    "last_updated": "2026-07-15"
  },
  "vvodjiu": {
    "balance": 3.391,
    "total_sent": 42,
    "last_updated": "2026-07-15"
  },
  "blueoctopus": {
    "balance": 1.911,
    "total_sent": 21,
    "last_updated": "2026-07-15"
  },
  "hopefulsoul": {
    "balance": 1.666,
    "total_sent": 15,
    "last_updated": "2026-07-15"
  },
  "ronimarie82": {
    "balance": 1.135,
    "total_sent": 12,
    "last_updated": "2026-07-15"
  },
  "lj1728": {
    "balance": 4.292,
    "total_sent": 36,
    "last_updated": "2026-07-15"
  },
  "antonette": {
    "balance": 0.421,
    "total_sent": 5,
    "last_updated": "2026-05-26"
  },
  "krissymayol": {
    "balance": 0.79,
    "total_sent": 8,
    "last_updated": "2026-07-15"
  },
  "wanderelle": {
    "balance": 0.787,
    "total_sent": 8,
    "last_updated": "2026-07-15"
  },
  "crstypatata": {
    "balance": 0.69,
    "total_sent": 8,
    "last_updated": "2026-07-15"
  },
  "mayt": {
    "balance": 2.603,
    "total_sent": 9,
    "last_updated": "2026-07-15"
  },
  "lolitaanana001": {
    "balance": 2.468,
    "total_sent": 15,
    "last_updated": "2026-07-15"
  },
  "jocabanero4": {
    "balance": 0.77,
    "total_sent": 3,
    "last_updated": "2026-04-22"
  },
  "izyllah-aeon": {
    "balance": 2.116,
    "total_sent": 6,
    "last_updated": "2026-07-15"
  },
  "saijan19": {
    "balance": 1.389,
    "total_sent": 3,
    "last_updated": "2026-07-15"
  },
  "celestyne15": {
    "balance": 1.363,
    "total_sent": 3,
    "last_updated": "2026-07-15"
  },
  "heymariel": {
    "balance": 1.36,
    "total_sent": 3,
    "last_updated": "2026-07-15"
  },
  "rabino7515": {
    "balance": 1.354,
    "total_sent": 3,
    "last_updated": "2026-07-15"
  },
  "desyah07": {
    "balance": 1.525,
    "total_sent": 2,
    "last_updated": "2026-07-15"
  },
  "gracefulwrites": {
    "balance": 1.639,
    "total_sent": 1,
    "last_updated": "2026-07-15"
  },
  "rizz26": {
    "balance": 1.973,
    "total_sent": 2,
    "last_updated": "2026-07-15"
  },
  "daileen23": {
    "balance": 1.601,
    "total_sent": 1,
    "last_updated": "2026-07-15"
  },
  "arriane001": {
    "balance": 1.206,
    "total_sent": 2,
    "last_updated": "2026-07-15"
  },
  "sammify": {
    "balance": 0.562,
    "total_sent": 1,
    "last_updated": "2026-07-15"
  },
  "joanna112890": {
    "balance": 1.301,
    "total_sent": 0,
    "last_updated": "2026-07-15"
  },
  "yhanyx87": {
    "balance": 1.23,
    "total_sent": 0,
    "last_updated": "2026-07-15"
  },
  "honeyjean24": {
    "balance": 0.882,
    "total_sent": 0,
    "last_updated": "2026-07-15"
  },
  "segundolhou29": {
    "balance": 0,
    "total_sent": 0,
    "last_updated": "2026-07-15"
  },
  "hmayak": {
    "balance": 0.802,
    "total_sent": 0,
    "last_updated": "2026-07-15"
  },
  "olang23": {
    "balance": 0.333,
    "total_sent": 0,
    "last_updated": "2026-04-22"
  },
  "rodavlas": {
    "balance": 0.402,
    "total_sent": 0,
    "last_updated": "2026-04-20"
  },
  "levieshome": {
    "balance": 0.054,
    "total_sent": 0,
    "last_updated": "2026-04-20"
  },
  "serram007": {
    "balance": 0.116,
    "total_sent": 0,
    "last_updated": "2026-04-22"
  },
  "jovan1978": {
    "balance": 1.455,
    "total_sent": 0,
    "last_updated": "2026-07-15"
  },
  "mdsahin111": {
    "balance": 4.207,
    "total_sent": 0,
    "last_updated": "2026-07-15"
  }
}