{
  "gretelarmfeg": {
    "balance": 4.332,
    "total_sent": 0,
    "last_updated": "2026-02-17"
  },
  "suteru": {
    "balance": 3.944,
    "total_sent": 0,
    "last_updated": "2026-02-17"
  },
  "diosarich": {
    "balance": 3.739,
    "total_sent": 0,
    "last_updated": "2026-02-17"
  },
  "vinzie1": {
    "balance": 3.161,
    "total_sent": 0,
    "last_updated": "2026-02-17"
  },
  "katiekate86": {
    "balance": 1.975,
    "total_sent": 0,
    "last_updated": "2026-02-17"
  },
  "jeanieviv84": {
    "balance": 1.59,
    "total_sent": 0,
    "last_updated": "2026-02-17"
  },
  "dreamrona": {
    "balance": 1.186,
    "total_sent": 0,
    "last_updated": "2026-02-17"
  },
  "vvodjiu": {
    "balance": 0.986,
    "total_sent": 0,
    "last_updated": "2026-02-17"
  },
  "blueoctopus": {
    "balance": 0.786,
    "total_sent": 0,
    "last_updated": "2026-02-17"
  },
  "hopefulsoul": {
    "balance": 0.755,
    "total_sent": 0,
    "last_updated": "2026-02-17"
  },
  "jocabanero4": {
    "balance": 0.605,
    "total_sent": 0,
    "last_updated": "2026-02-17"
  },
  "ronimarie82": {
    "balance": 0.594,
    "total_sent": 0,
    "last_updated": "2026-02-17"
  },
  "lj1728": {
    "balance": 0.591,
    "total_sent": 0,
    "last_updated": "2026-02-17"
  },
  "antonette": {
    "balance": 0.399,
    "total_sent": 0,
    "last_updated": "2026-02-17"
  },
  "krissymayol": {
    "balance": 0.397,
    "total_sent": 0,
    "last_updated": "2026-02-17"
  },
  "wanderelle": {
    "balance": 0.397,
    "total_sent": 0,
    "last_updated": "2026-02-17"
  },
  "crstypatata": {
    "balance": 0.394,
    "total_sent": 0,
    "last_updated": "2026-02-17"
  },
  "mayt": {
    "balance": 0.394,
    "total_sent": 0,
    "last_updated": "2026-02-17"
  },
  "lolitaanana001": {
    "balance": 0.391,
    "total_sent": 0,
    "last_updated": "2026-02-17"
  },
  "izyllah-aeon": {
    "balance": 0.367,
    "total_sent": 0,
    "last_updated": "2026-02-17"
  },
  "saijan19": {
    "balance": 0.198,
    "total_sent": 0,
    "last_updated": "2026-02-17"
  },
  "celestyne15": {
    "balance": 0.198,
    "total_sent": 0,
    "last_updated": "2026-02-17"
  },
  "heymariel": {
    "balance": 0.197,
    "total_sent": 0,
    "last_updated": "2026-02-17"
  },
  "rabino7515": {
    "balance": 0.197,
    "total_sent": 0,
    "last_updated": "2026-02-17"
  },
  "desyah07": {
    "balance": 0.16,
    "total_sent": 0,
    "last_updated": "2026-02-17"
  },
  "gracefulwrites": {
    "balance": 0.118,
    "total_sent": 0,
    "last_updated": "2026-02-17"
  },
  "rizz26": {
    "balance": 0.118,
    "total_sent": 0,
    "last_updated": "2026-02-17"
  },
  "daileen23": {
    "balance": 0.118,
    "total_sent": 0,
    "last_updated": "2026-02-17"
  },
  "arriane001": {
    "balance": 0.098,
    "total_sent": 0,
    "last_updated": "2026-02-17"
  },
  "sammify": {
    "balance": 0.072,
    "total_sent": 0,
    "last_updated": "2026-02-17"
  },
  "yhanyx87": {
    "balance": 0.055,
    "total_sent": 0,
    "last_updated": "2026-02-17"
  },
  "honeyjean24": {
    "balance": 0.039,
    "total_sent": 0,
    "last_updated": "2026-02-17"
  },
  "segundolhou29": {
    "balance": 0,
    "total_sent": 0,
    "last_updated": "2026-02-17"
  },
  "_meta": {
    "last_accumulated_date": "2026-02-16"
  }
}