{
  "date": "2026-02-21",
  "total_delegation_hp": 7310.185,
  "total_curation_hive": 1.179467,
  "distributable_hive": 1.120494,
  "delegators": [
    {
      "name": "gretelarmfeg",
      "hp": 1107.725,
      "base_reward": 0.16979
    },
    {
      "name": "suteru",
      "hp": 1008.097,
      "base_reward": 0.154519
    },
    {
      "name": "diosarich",
      "hp": 956.038,
      "base_reward": 0.14654
    },
    {
      "name": "vinzie1",
      "hp": 808.309,
      "base_reward": 0.123896
    },
    {
      "name": "katiekate86",
      "hp": 504.927,
      "base_reward": 0.077394
    },
    {
      "name": "jeanieviv84",
      "hp": 406.356,
      "base_reward": 0.062286
    },
    {
      "name": "dreamrona",
      "hp": 302.778,
      "base_reward": 0.046409
    },
    {
      "name": "vvodjiu",
      "hp": 252.152,
      "base_reward": 0.038649
    },
    {
      "name": "blueoctopus",
      "hp": 201.148,
      "base_reward": 0.030832
    },
    {
      "name": "hopefulsoul",
      "hp": 192.775,
      "base_reward": 0.029548
    },
    {
      "name": "jocabanero4",
      "hp": 154.901,
      "base_reward": 0.023743
    },
    {
      "name": "ronimarie82",
      "hp": 152.007,
      "base_reward": 0.023299
    },
    {
      "name": "lj1728",
      "hp": 150.979,
      "base_reward": 0.023142
    },
    {
      "name": "antonette",
      "hp": 101.761,
      "base_reward": 0.015598
    },
    {
      "name": "krissymayol",
      "hp": 101.718,
      "base_reward": 0.015591
    },
    {
      "name": "wanderelle",
      "hp": 101.653,
      "base_reward": 0.015581
    },
    {
      "name": "crstypatata",
      "hp": 100.521,
      "base_reward": 0.015408
    },
    {
      "name": "mayt",
      "hp": 100.49,
      "base_reward": 0.015403
    },
    {
      "name": "lolitaanana001",
      "hp": 100.138,
      "base_reward": 0.015349
    },
    {
      "name": "izyllah-aeon",
      "hp": 93.936,
      "base_reward": 0.014398
    },
    {
      "name": "saijan19",
      "hp": 50.826,
      "base_reward": 0.007791
    },
    {
      "name": "celestyne15",
      "hp": 50.491,
      "base_reward": 0.007739
    },
    {
      "name": "heymariel",
      "hp": 50.457,
      "base_reward": 0.007734
    },
    {
      "name": "rabino7515",
      "hp": 50.376,
      "base_reward": 0.007722
    },
    {
      "name": "desyah07",
      "hp": 40.717,
      "base_reward": 0.006241
    },
    {
      "name": "gracefulwrites",
      "hp": 30.538,
      "base_reward": 0.004681
    },
    {
      "name": "rizz26",
      "hp": 30.477,
      "base_reward": 0.004671
    },
    {
      "name": "daileen23",
      "hp": 30.157,
      "base_reward": 0.004622
    },
    {
      "name": "arriane001",
      "hp": 25.188,
      "base_reward": 0.003861
    },
    {
      "name": "sammify",
      "hp": 18.122,
      "base_reward": 0.002778
    },
    {
      "name": "yhanyx87",
      "hp": 14.235,
      "base_reward": 0.002182
    },
    {
      "name": "honeyjean24",
      "hp": 10.185,
      "base_reward": 0.001561
    },
    {
      "name": "joanna112890",
      "hp": 10.007,
      "base_reward": 0.001534
    },
    {
      "name": "segundolhou29",
      "hp": 0,
      "base_reward": 0
    }
  ]
}